{
  "generator-jhipster": {
    "applicationType": "microservice",
    "authenticationType": "jwt",
    "baseName": "Halwarpoissonnerie",
    "blueprints": [],
    "buildTool": "maven",
    "cacheProvider": "hazelcast",
    "clientFramework": "angularX",
    "clientPackageManager": "npm",
    "clientTheme": "none",
    "clientThemeVariant": "",
    "creationTimestamp": 1672251846893,
    "databaseType": "sql",
    "devDatabaseType": "mysql",
    "devServerPort": 4200,
    "dtoSuffix": "DTO",
    "enableGradleEnterprise": false,
    "enableHibernateCache": true,
    "enableSwaggerCodegen": "true",
    "enableTranslation": true,
    "entitySuffix": "",
    "gitCompany": "",
    "jhiPrefix": "jhi",
    "jhipsterVersion": "7.9.3",
    "jwtSecretKey": "M2Y1ZDI2OGIyNWE5MWNlMzkzZjAxNzI2YjU5Y2RkYWMxYTk4OWJmZWZhNDE2N2I0MzgzY2U5NDk3MDcyOTc3OWY0MTRhZGZiY2Q5ZDcyNTQ0YTZjY2UyYjgwYmEyZTZiYjZjY2EyZTI3NzUxYzIwYTEyM2M3YjI4NWNmYTRhM2I=",
    "languages": ["fr", "en"],
    "messageBroker": "kafka",
    "microfrontend": false,
    "nativeLanguage": "fr",
    "otherModules": [],
    "packageFolder": "com/famira/halwarpoisonnerie",
    "packageName": "com.famira.halwarpoisonnerie",
    "pages": [],
    "prodDatabaseType": "mysql",
    "reactive": false,
    "searchEngine": "elasticsearch",
    "serverPort": 8081,
    "serviceDiscoveryType": "eureka",
    "skipCheckLengthOfIdentifier": false,
    "skipClient": false,
    "skipFakeData": false,
    "skipUserManagement": true,
    "testFrameworks": ["gatling"],
    "useSass": true,
    "websocket": false,
    "withAdminUi": false
  },
  "git-provider": "GitHub",
  "git-company": "tallahmad",
  "repository-name": "jhipster-halwar-poissonnerie"
}
